siunits/__init__.py
siunits/main.py
siunits/test_.py
siunits/units.py
siunits-0.0.6.dist-info/LICENSE
siunits-0.0.6.dist-info/METADATA
siunits-0.0.6.dist-info/WHEEL
siunits-0.0.6.dist-info/top_level.txt
siunits-0.0.6.dist-info/RECORD
