Metadata-Version: 2.1
Name: siunits
Version: 0.0.6
Summary: Perform operations on SI units
Home-page: https://github.com/David-OConnor/si_units
Author: David O'Connor
Author-email: david.alan.oconnor@gmail.com
License: MIT
Keywords: si units dimensional analysis
Platform: UNKNOWN
Classifier: Programming Language :: Python :: 3 :: Only
Classifier: License :: OSI Approved :: MIT License
Classifier: Operating System :: OS Independent
Classifier: Topic :: Scientific/Engineering
Requires-Python: >=3.7
